wikicite/__init__.py
wikicite/create_citation.py
wikicite/get_reference_name.py
wikicite/links.toml
wikicite/markdown.py
wikicite/options.py
wikicite/sources.toml
wikicite/wikicite.py
wikicite-0.3.0.dist-info/entry_points.txt
wikicite-0.3.0.dist-info/METADATA
wikicite-0.3.0.dist-info/WHEEL
wikicite-0.3.0.dist-info/RECORD
