Metadata-Version: 2.1
Name: wikicite
Version: 0.3.0
Summary: Create ready-to-use Wikipedia citations from a series of inputs
Author: peaky76
Author-email: robertjamespeacock@gmail.com
Requires-Python: >=3.11,<4.0
Classifier: Programming Language :: Python :: 3
Classifier: Programming Language :: Python :: 3.11
Requires-Dist: click (>=8.1.3,<9.0.0)
Requires-Dist: pyyaml (>=6.0,<7.0)
